{
            "books": [

        {
            "title": "The Lord of the Rings: Fellowship of the Ring",
            "director": ["Peter Jackson"],
            "filmLenght": "2 hours and 58 minutes",
            "thumbnail": "/images/OIP.jpg",
            "categories": []
         },
         {
            "title": "Fantastic Mr. Fox",
            "director": ["Wes Anderson"],
            "filmLenght": "1 hour and 27 minutes",
            "thumbnail": "/images/jAFvXFcup7pQOyofJlxPr6rcFaa.jpg",
            "categories": []
         },
         {
            "title": "Jujutsu Kaisen 0",
            "director": ["Sunghoo Park"],
            "filmLenght": "1 hour and 52minutes",
            "thumbnail": "/images/OIP (1).jpg",
            "categories": []
         } 
    ]
}
